sec_form_d/__init__.py
sec_form_d/analysis.py
sec_form_d/comparison/__init__.py
sec_form_d/comparison/comparison_utils.py
sec_form_d/comparison/difference.py
sec_form_d/constants.py
sec_form_d/enums.py
sec_form_d/exceptions.py
sec_form_d/logger.py
sec_form_d/parser.py
sec_form_d/parsing/__init__.py
sec_form_d/parsing/fields/__init__.py
sec_form_d/parsing/fields/base_fields.py
sec_form_d/parsing/fields/checkboxes.py
sec_form_d/parsing/fields/data_fields.py
sec_form_d/parsing/schema_extraction.py
sec_form_d/parsing/sections.py
sec_form_d/types/__init__.py
sec_form_d/types/diff.py
sec_form_d/types/field.py
sec_form_d/types/form.py
sec_form_d/types/schema.py
sec_form_d/types/section.py
sec_form_d/utils.py
sec_form_d/validators/__init__.py
sec_form_d/validators/html.py
sec_form_d/validators/validator.py
sec_form_d-0.1.0.dist-info/LICENSE
sec_form_d-0.1.0.dist-info/METADATA
sec_form_d-0.1.0.dist-info/WHEEL
sec_form_d-0.1.0.dist-info/RECORD
